j/__init__.py
jsonp-1.0.4.dist-info/entry_points.txt
jsonp-1.0.4.dist-info/WHEEL
jsonp-1.0.4.dist-info/METADATA
jsonp-1.0.4.dist-info/RECORD
