Metadata-Version: 1.1
Name: jsonp
Version: 1.0.4
Summary: Simple pipeline json parser
Home-page: https://github.com/paul-nameless/j
Author: Paul Nameless
Author-email: paul.nameless@icloud.com
